{"KHg24Q1Ld9PR0I8dhWuz9g==":"asset-64x-343x51.png","1nqey1c50SYIUWH7ChEFqA==":"mbr-1-1920x1280.jpg","MSKwX02bKQKotlZ8xhg7iQ==":"asset-132x-1466x200.png","iLbIJw0DQGCm1T7tLd5W6w==":"mbr-178x178.jpg","Z65StI010GmI+Jz8ofAnjw==":"mbr-1920x1280.jpg","eUpD3bSvm3tHfPz189YJ9Q==":"mbr-1920x672.jpg","T8XMxtrz5me+AlGPeMiCGA==":"system-management-106x106.png","vChsOv0nrQZ5NqkRHFDZHg==":"mbr-1920x711.jpg","F9wIgrfJ+zcF1NUkYOwYlw==":"networking-icon-158x158.png","cK8nfnXMrjaddcgeV2Zhug==":"mbr-1920x1024.jpg","CLxNfR48O12S4k52THjfrg==":"veryfi-is-phipa-compliant-472x221.png","hoImJ/6nLVVVioWyE573rA==":"helpdesk-127x127.png","iV3WDwt1r1LcyDjJ4KG7IQ==":"mbr-1-1918x707.jpg","nLKeVkqf/BbcoETdW5Mzjw==":"mbr-952x635.jpg","SzeoxeSUZ7xF/G/NiG+POA==":"background4-1920x1280.jpg","PGS2H8sL36FteAcXcm5Mjw==":"gettyimages-1406680086-2000x739.jpg","1dxOT7jbqRcOWiOtvJ4O6g==":"amazon%20card-436x393.png","iNnjfQK/mkvEXbpFZRtF0A==":"gettyimages-1770757858-402x268.jpg","JkTWu6Fk0rgwd5OJ6YpsIQ==":"gettyimages-2148123501-402x206.jpg","WiN2cloEkIGWGjV7p1YHlg==":"gettyimages-2148123501-402x206.jpeg","doJcn720pBPw625JdX1+GQ==":"gettyimages-2148123502-402x206.jpeg","/mHSyuoyn6TV3puwvEQCUg==":"gettyimages-2148123503-402x206.jpeg","NDxmGaAiPAA09tArrgbaPA==":"gettyimages-2148123504-402x206.jpeg","waEsxJOQby3dDAkyqfXhsQ==":"gettyimages-2148123505-402x206.jpeg","Ux1LMUirNiKOZKzXIUhhJg==":"gettyimages-943065362-402x226.jpg","7wqEl6DWO8NtI+sBlmZvtg==":"gettyimages-943065362-402x226.jpeg","uYSO4xbLnJT856S/Y4pJ6w==":"gettyimages-943065363-402x226.jpeg","enjeu8BS98RD80KVRuy+4A==":"gettyimages-943065364-402x226.jpeg","8Z0sCQo+/ZInkw2TDg9HUw==":"gettyimages-1068618692-402x268.jpg","TQAouLxUjFtLgWlTph6A7g==":"gettyimages-1456739978-402x226.jpg","Wxn7HLGp+pAYGIdI1gePDQ==":"gettyimages-1456739978-402x226.jpeg","UFSnQQ7VXXVStS/qz7CEvQ==":"gettyimages-1456739979-402x226.jpeg","sjJFIMxQql4eJs1ULX4Wyg==":"gettyimages-1456739980-402x226.jpeg","jQS7XCnz+GTM5W2oR6FFBg==":"gettyimages-1473508659-402x223.jpg","yfAr3Y5qUQRalhCWcKN3Ag==":"gettyimages-1473508659-402x223.jpeg","xJOWq8m3MSxgkX0WqIajbQ==":"gettyimages-1473508660-402x223.jpeg","CTmL0W1xiL/t9OIxscVqsA==":"gettyimages-1141238007%20education%20banner-2000x600.png","Nrew57pk3FGjJk4z9gpDdQ==":"gettyimages-973856430-2000x666.jpg","2j6zfj7FWZlvZRVtbLhscw==":"header%20-%20referal%20page-1692x334.png","nVoZ8/wi4F+mEaDF+9LKpg==":"header%20-%20referal%20page-1692x334.png","38mq1f5Nry+wU0cboYnrUA==":"header%20-%20referal%20page-1692x334.png","3WgPjzwvRNyMJwZPaTdcjA==":"header%20-%20referal%20page-1270x304.png","sFEpMxoGlld2Prvap3aCnA==":"amazon%20gift%20card-436x322.png","XpZ3zD3gskKcxwBxOlmyDg==":"footer%20-%20referal%20page-1261x346.png","LQIqxurWm7gPeVBxbJuxuw==":"footer%20-%20referal%20page-1261x346.png","FR7QItaMkj5QsytQzWdP1w==":"footer%20-%20referal%20page-1261x346.png","yqHRFRYJ44/KT3birEJO9w==":"footer%20-%20referal%20page-1261x346.png","DcKo/rbbRxnc0CTifl3vAQ==":"footer%20-%20referal%20page-1261x346.png","ZimJqZnW5GB386NJOX/iHA==":"gettyimages-1623947749-2000x1333.jpg","/Rxye9RgA9KDAWe9742zQA==":"background3.jpeg","iUE/U3WknhOtYIqqPajUfA==":"gettyimages-1623947749-699x466.jpg","z3HXmQbv+igjUfDZMZU0Tg==":"gettyimages-1161029738-2000x1174.jpg","h5LlCogVh+76AHA6yYE2HQ==":"gettyimages-1161029738-699x410.jpg","YRF0vSWk9IjRNQk0z9k5cw==":"gettyimages-1161029738-699x410.jpeg","lQhH9aIuXDrgCRU0cvDMhQ==":"gettyimages-1161029739-699x410.jpeg","MkzLNA6LJ5I+RKYQEjUlTQ==":"gettyimages-1161029740-699x410.jpeg","XCW6kg7Dkcai14PVVExLyg==":"gettyimages-1161029741-699x410.jpeg","OnW/2oDX70EC8oFnBEZsBg==":"gettyimages-1161029742-699x410.jpeg","IvQEMTGuM+wunXTdMb9uMQ==":"gettyimages-1332104710-699x369.jpg","/zFCYyq31EHiB2XiPzlqvA==":"gettyimages-1332104710-699x369.jpeg","POQU+OzJqMx92jLi+4CLlw==":"gettyimages-1332104711-699x369.jpeg","Pf2asL3jdfvzLkAYkpr0xQ==":"gettyimages-1332104712-699x369.jpeg","m+3v4+/ZZ4A2OOsX9rBHfQ==":"gettyimages-1332104713-699x369.jpeg","NbwfNaapc612TS2+E0HXwQ==":"gettyimages-1332104714-699x369.jpeg","3CS0P4BPOC3vw/xAn60gJA==":"gettyimages-1332104715-699x369.jpeg","SM1Z9XVUmvno2EuoR0MD0w==":"gettyimages-1332104716-699x369.jpeg","f5ub5PdhCPDvu8kCdLvRPQ==":"gettyimages-1332104717-699x369.jpeg","xbdeQAhQkp6LuXRAaXQqKQ==":"gettyimages-1332104710-2000x1055.jpg","02yypVlzIF7R580AYWZlUw==":"gettyimages-1332104710-2000x1055.jpeg","pHgUewYeY4pBmlqBqDMCMg==":"gettyimages-1777088857-2000x1125.jpg","RSvu/Lgh0hvWREL1y0SmYQ==":"gettyimages-1930821680-2000x1333.jpg","Splpd2t85x/j1MHuTreX+g==":"gettyimages-1480574757-2000x920.jpg","D1U738S3IiBJv0bLoCdAOw==":"gettyimages-1480574757-2000x920.jpeg","awgS7cqGC345mKAKdlU6Nw==":"gettyimages-1765735122-2000x1333.jpg","PMy0pcYP6Hjca8EV9NDJMw==":"gettyimages-1765735122-675x450.jpg","QJybu9yWiYvLHNUduVxx4g==":"white%20square-675x674.jpg","dI28rmcML/te8h2jZmjRkA==":"gettyimages-1777088857-675x380.jpg","q0ixT/mm3mqC3PBTM+wdOw==":"gettyimages-1777088857-675x380.jpeg","77s8fcKo6TtGyfAe5Xc8aA==":"gettyimages-1777088858-675x380.jpeg","t0njcxE2iF8NRj0l3bFkZQ==":"dividing%20line-499x76.png","iI7tpNdIBucnnQ1aoB28gQ==":"dividing%20line-1465x66.png","2KS0sHujuG3G2ApfUFadMQ==":"dividing%20line-1431x84.png","m4dWyvFX0NBCOd/DJD0jrg==":"dividing%20line-1431x84.png","91/2baxc5TybJXRiIMCCnw==":"dividing%20line-1431x84.png","/OgtdXIUFCPNgiGptjE01w==":"gettyimages-1930821680-675x450.jpg","BO/hSYaPrLC7vWZVukB0Rw==":"4944443615634362035-300x168.jpg","hKPcarSQ+OQ0EVR9nH9keg==":"4944443615634362035-300x168.jpeg","PFaTQ/uJmUd7KA0FLCVALQ==":"4944443615634362035-1-300x168.jpeg","fF9USqiw1W4LO7PXvcSbzA==":"4944443615634362035-301x168.jpeg","TX7wY/ZPQZitgrJolPvyRQ==":"4944443615634362035-406x227.jpeg","eDBOtfKUbPzNZRfM+vZu1Q==":"gettyimages-1567607159-241x135.jpeg"}